setup.cfg
setup.py
nicer/__init__.py
nicer/bits.py
nicer/eqs.py
nicer/slices.py
nicer/times.py
nicer/version.py
nicer.egg-info/PKG-INFO
nicer.egg-info/SOURCES.txt
nicer.egg-info/dependency_links.txt
nicer.egg-info/top_level.txt