Metadata-Version: 1.0
Name: nicer
Version: 0.0.5
Summary: Nicer: Utils package
Home-page: https://github.com/netanelrevah/nicer
Author: netanelrevah
Author-email: netanelrevah@users.noreply.github.com
License: GNU General Public License, version 2
Keywords: utils nicer
Platform: UNKNOWN
